<?xml version="1.0" encoding="utf-8"?><CoordinateList><Page nb="1"><Line nb="1"><Entity><String>i</String><Coordinate>1129-34-7-9-1</Coordinate><ConfidenceRateList>-30</ConfidenceRateList></Entity><Entity><String>*.</String><Coordinate>1166-23-22-16-1</Coordinate><ConfidenceRateList>-30-30</ConfidenceRateList></Entity></Line><Line nb="2"><Entity><String>1</String><Coordinate>1124-43-13-20-1</Coordinate><ConfidenceRateList>-69</ConfidenceRateList></Entity></Line><Line nb="3"><Entity><String>lib</String><Coordinate>34-19-15-10-1</Coordinate><ConfidenceRateList>-69-30-30</ConfidenceRateList></Entity></Line><Line nb="4"><Entity><String>49</String><Coordinate>1113-66-12-22-1</Coordinate><ConfidenceRateList>-30-30</ConfidenceRateList></Entity></Line><Line nb="5"><Entity><String>r.</String><Coordinate>15-36-10-7-1</Coordinate><ConfidenceRateList>-30-30</ConfidenceRateList></Entity></Line><Line nb="6"><Entity><String>'</String><Coordinate>1108-96-10-10-1</Coordinate><ConfidenceRateList>-30</ConfidenceRateList></Entity><Entity><String>ulik</String><Coordinate>1143-102-43-33-1</Coordinate><ConfidenceRateList>-69-69-30-30</ConfidenceRateList></Entity></Line><Line nb="7"><Entity><String>wcj</String><Coordinate>35-75-54-29-1</Coordinate><ConfidenceRateList>-69-30-30</ConfidenceRateList></Entity><Entity><String>#</String><Coordinate>174-79-10-14-1</Coordinate><ConfidenceRateList>-30</ConfidenceRateList></Entity></Line><Line nb="8"><Entity><String>[</String><Coordinate>396-94-39-84-1</Coordinate><ConfidenceRateList>-100</ConfidenceRateList></Entity><Entity><String>.1</String><Coordinate>461-102-3-6-1</Coordinate><ConfidenceRateList>-30-30</ConfidenceRateList></Entity><Entity><String>OH</String><Coordinate>497-102-159-69-1</Coordinate><ConfidenceRateList>-85-30</ConfidenceRateList></Entity><Entity><String>MI</String><Coordinate>680-103-131-88-1</Coordinate><ConfidenceRateList>-30-30</ConfidenceRateList></Entity></Line><Line nb="9"><Entity><String>„</String><Coordinate>26-152-7-8-1</Coordinate><ConfidenceRateList>-30</ConfidenceRateList></Entity></Line><Line nb="10"><Entity><String>le</String><Coordinate>1103-203-20-17-1</Coordinate><ConfidenceRateList>-30-30</ConfidenceRateList></Entity><Entity><String>A</String><Coordinate>1140-210-34-30-1</Coordinate><ConfidenceRateList>-30</ConfidenceRateList></Entity></Line><Line nb="11"><Entity><String>.</String><Coordinate>206-193-2-2-1</Coordinate><ConfidenceRateList>-30</ConfidenceRateList></Entity><Entity><String>.</String><Coordinate>223-197-1-1-1</Coordinate><ConfidenceRateList>-30</ConfidenceRateList></Entity></Line><Line nb="12"><Entity><String>.</String><Coordinate>182-200-2-2-1</Coordinate><ConfidenceRateList>-30</ConfidenceRateList></Entity><Entity><String>.</String><Coordinate>194-205-1-1-1</Coordinate><ConfidenceRateList>-30</ConfidenceRateList></Entity></Line><Line nb="13"><Entity><String>Granite</String><Coordinate>465-224-104-23-1</Coordinate><ConfidenceRateList>-100-100-100-100-100-100-100</ConfidenceRateList></Entity><Entity><String>Run</String><Coordinate>588-228-43-24-1</Coordinate><ConfidenceRateList>-100-100-100</ConfidenceRateList></Entity><Entity><String>Mall</String><Coordinate>650-231-55-23-1</Coordinate><ConfidenceRateList>-100-100-100-100</ConfidenceRateList></Entity></Line><Line nb="14"><Entity><String>Media</String><Coordinate>464-257-73-22-1</Coordinate><ConfidenceRateList>-100-100-100-100-100</ConfidenceRateList></Entity><Entity><String>PA</String><Coordinate>572-261-27-21-1</Coordinate><ConfidenceRateList>-100-100</ConfidenceRateList></Entity><Entity><String>19063</String><Coordinate>620-263-71-23-1</Coordinate><ConfidenceRateList>-100-100-100-100-100</ConfidenceRateList></Entity></Line><Line nb="15"><Entity><String>.</String><Coordinate>156-260-1-2-1</Coordinate><ConfidenceRateList>-30</ConfidenceRateList></Entity><Entity><String>.</String><Coordinate>182-261-3-3-1</Coordinate><ConfidenceRateList>-30</ConfidenceRateList></Entity></Line><Line nb="16"><Entity><String>:1</String><Coordinate>65-280-8-19-1</Coordinate><ConfidenceRateList>-30-30</ConfidenceRateList></Entity><Entity><String>.</String><Coordinate>80-280-1-1-1</Coordinate><ConfidenceRateList>-30</ConfidenceRateList></Entity><Entity><String>.</String><Coordinate>93-307-2-1-1</Coordinate><ConfidenceRateList>-30</ConfidenceRateList></Entity><Entity><String>t'</String><Coordinate>115-282-8-8-1</Coordinate><ConfidenceRateList>-30-30</ConfidenceRateList></Entity><Entity><String>•</String><Coordinate>130-287-1-1-1</Coordinate><ConfidenceRateList>-30</ConfidenceRateList></Entity><Entity><String>.</String><Coordinate>151-303-1-1-1</Coordinate><ConfidenceRateList>-30</ConfidenceRateList></Entity><Entity><String>41:</String><Coordinate>212-268-17-32-1</Coordinate><ConfidenceRateList>-30-30-30</ConfidenceRateList></Entity><Entity><String>..</String><Coordinate>234-301-8-5-1</Coordinate><ConfidenceRateList>-30-30</ConfidenceRateList></Entity></Line><Line nb="17"><Entity><String>.</String><Coordinate>210-317-2-2-1</Coordinate><ConfidenceRateList>-30</ConfidenceRateList></Entity><Entity><String>.</String><Coordinate>239-314-5-4-1</Coordinate><ConfidenceRateList>-30</ConfidenceRateList></Entity><Entity><String>(610)</String><Coordinate>479-290-73-23-1</Coordinate><ConfidenceRateList>-100-100-100-100-100</ConfidenceRateList></Entity><Entity><String>627</String><Coordinate>571-294-43-23-1</Coordinate><ConfidenceRateList>-100-100-100</ConfidenceRateList></Entity><Entity><String>2600</String><Coordinate>632-296-58-23-1</Coordinate><ConfidenceRateList>-100-100-100-100</ConfidenceRateList></Entity></Line><Line nb="18"><Entity><String>4</String><Coordinate>1126-358-18-19-1</Coordinate><ConfidenceRateList>-69</ConfidenceRateList></Entity><Entity><String>..</String><Coordinate>1146-374-9-6-1</Coordinate><ConfidenceRateList>-30-30</ConfidenceRateList></Entity></Line><Line nb="19"><Entity><String>.</String><Coordinate>6-345-10-10-1</Coordinate><ConfidenceRateList>-30</ConfidenceRateList></Entity><Entity><String>01</String><Coordinate>267-345-22-22-1</Coordinate><ConfidenceRateList>-100-100</ConfidenceRateList></Entity><Entity><String>23</String><Coordinate>312-347-27-22-1</Coordinate><ConfidenceRateList>-100-100</ConfidenceRateList></Entity><Entity><String>15</String><Coordinate>359-349-25-23-1</Coordinate><ConfidenceRateList>-30-30</ConfidenceRateList></Entity><Entity><String>12:58P</String><Coordinate>404-351-86-23-1</Coordinate><ConfidenceRateList>-100-100-100-100-100-100</ConfidenceRateList></Entity><Entity><String>0278/0007/8918/0</String><Coordinate>539-356-240-22-1</Coordinate><ConfidenceRateList>-100-100-100-100-100-100-100-100-100-100-100-100-100-100-100-100</ConfidenceRateList></Entity><Entity><String>2504XXX</String><Coordinate>797-366-105-23-1</Coordinate><ConfidenceRateList>-100-100-100-30-30-100-30</ConfidenceRateList></Entity></Line><Line nb="20"><Entity><String>11:4;</String><Coordinate>1146-401-47-47-1</Coordinate><ConfidenceRateList>-69-69-69-30-30</ConfidenceRateList></Entity></Line><Line nb="21"><Entity><String>".</String><Coordinate>170-424-4-2-1</Coordinate><ConfidenceRateList>-30-30</ConfidenceRateList></Entity></Line><Line nb="22"><Entity><String>4141</String><Coordinate>0-360-103-90-1</Coordinate><ConfidenceRateList>-69-69-30-30</ConfidenceRateList></Entity><Entity><String>IDtt</String><Coordinate>269-377-40-22-1</Coordinate><ConfidenceRateList>-100-85-30-30</ConfidenceRateList></Entity><Entity><String>99998768487_4188_9721....921o_8203</String><Coordinate>327-379-496-23-1</Coordinate><ConfidenceRateList>-100-100-100-100-100-100-100-100-100-100-100-30-100-100-100-100-30-100-100-100-100-69-69-69-69-100-100-100-30-30-100-100-100-100</ConfidenceRateList></Entity><Entity><String>8487</String><Coordinate>463-385-57-22-1</Coordinate><ConfidenceRateList>-100-100-100-100</ConfidenceRateList></Entity><Entity><String>4188</String><Coordinate>539-389-56-23-1</Coordinate><ConfidenceRateList>-100-100-100-100</ConfidenceRateList></Entity><Entity><String>97219210</String><Coordinate>614-391-133-22-1</Coordinate><ConfidenceRateList>-100-100-100-100-100-100-100-30</ConfidenceRateList></Entity><Entity><String>8203</String><Coordinate>765-396-58-23-1</Coordinate><ConfidenceRateList>-100-100-100-100</ConfidenceRateList></Entity><Entity><String>.e</String><Coordinate>1109-405-10-8-1</Coordinate><ConfidenceRateList>-30-30</ConfidenceRateList></Entity></Line><Line nb="23"><Entity><String>OCCASION</String><Coordinate>269-440-117-23-1</Coordinate><ConfidenceRateList>-100-100-100-100-100-100-100-100</ConfidenceRateList></Entity><Entity><String>FRAMES</String><Coordinate>403-445-87-23-1</Coordinate><ConfidenceRateList>-100-100-100-100-100-100</ConfidenceRateList></Entity><Entity><String>400954469364</String><Coordinate>508-449-175-22-1</Coordinate><ConfidenceRateList>-100-100-100-100-100-100-30-100-100-100-100-100</ConfidenceRateList></Entity><Entity><String>*</String><Coordinate>718-461-10-14-1</Coordinate><ConfidenceRateList>-100</ConfidenceRateList></Entity><Entity><String>3.99</String><Coordinate>791-460-59-23-1</Coordinate><ConfidenceRateList>-100-100-100-100</ConfidenceRateList></Entity><Entity><String>Ti</String><Coordinate>883-463-22-20-1</Coordinate><ConfidenceRateList>-100-30</ConfidenceRateList></Entity></Line><Line nb="24"><Entity><String>.</String><Coordinate>1179-496-2-2-1</Coordinate><ConfidenceRateList>-30</ConfidenceRateList></Entity><Entity><String>.</String><Coordinate>1197-497-3-3-1</Coordinate><ConfidenceRateList>-30</ConfidenceRateList></Entity></Line><Line nb="25"><Entity><String>4</String><Coordinate>204-462-25-27-1</Coordinate><ConfidenceRateList>-100</ConfidenceRateList></Entity><Entity><String>ItemPrice</String><Coordinate>301-471-128-21-1</Coordinate><ConfidenceRateList>-100-100-100-100-100-100-30-100-100</ConfidenceRateList></Entity><Entity><String>19.99</String><Coordinate>449-478-70-21-1</Coordinate><ConfidenceRateList>-100-100-30-100-100</ConfidenceRateList></Entity><Entity><String>YouSeve</String><Coordinate>582-483-100-22-1</Coordinate><ConfidenceRateList>-30-100-100-100-30-100-100</ConfidenceRateList></Entity><Entity><String>16.00</String><Coordinate>702-488-70-22-1</Coordinate><ConfidenceRateList>-100-100-100-100-100</ConfidenceRateList></Entity></Line><Line nb="26"><Entity><String>MISSES</String><Coordinate>271-501-86-23-1</Coordinate><ConfidenceRateList>-100-100-100-100-100-100</ConfidenceRateList></Entity><Entity><String>CAPRIS</String><Coordinate>374-505-86-23-1</Coordinate><ConfidenceRateList>-100-30-100-100-100-100</ConfidenceRateList></Entity><Entity><String>400938500793</String><Coordinate>507-510-173-22-1</Coordinate><ConfidenceRateList>-100-100-100-100-100-100-100-100-100-100-100-100</ConfidenceRateList></Entity><Entity><String>G</String><Coordinate>713-519-12-21-1</Coordinate><ConfidenceRateList>-30</ConfidenceRateList></Entity><Entity><String>7.20</String><Coordinate>789-521-56-23-1</Coordinate><ConfidenceRateList>-100-100-100-100</ConfidenceRateList></Entity><Entity><String>16</String><Coordinate>879-524-24-22-1</Coordinate><ConfidenceRateList>-100-100</ConfidenceRateList></Entity></Line><Line nb="27"><Entity><String>ItemPrice</String><Coordinate>302-532-127-21-1</Coordinate><ConfidenceRateList>-100-100-100-100-100-100-30-100-100</ConfidenceRateList></Entity><Entity><String>36.00</String><Coordinate>448-538-70-21-1</Coordinate><ConfidenceRateList>-100-100-100-100-100</ConfidenceRateList></Entity><Entity><String>YouSave</String><Coordinate>580-543-99-21-1</Coordinate><ConfidenceRateList>-30-100-100-100-100-100-100</ConfidenceRateList></Entity><Entity><String>28.80</String><Coordinate>697-548-71-22-1</Coordinate><ConfidenceRateList>-100-100-100-100-100</ConfidenceRateList></Entity></Line><Line nb="28"><Entity><String>•</String><Coordinate>1065-623-3-4-1</Coordinate><ConfidenceRateList>-30</ConfidenceRateList></Entity><Entity><String>H4</String><Coordinate>88-550-55-39-1</Coordinate><ConfidenceRateList>-69-69</ConfidenceRateList></Entity><Entity><String>GIRLS</String><Coordinate>272-561-71-22-1</Coordinate><ConfidenceRateList>-100-100-100-100-100</ConfidenceRateList></Entity><Entity><String>LINGERIE</String><Coordinate>360-564-115-22-1</Coordinate><ConfidenceRateList>-100-100-100-100-100-100-100-100</ConfidenceRateList></Entity><Entity><String>046094526415</String><Coordinate>506-571-172-21-1</Coordinate><ConfidenceRateList>-100-100-100-100-100-100-100-100-100-100-100-100</ConfidenceRateList></Entity><Entity><String>G</String><Coordinate>710-578-12-21-1</Coordinate><ConfidenceRateList>-30</ConfidenceRateList></Entity><Entity><String>2.40</String><Coordinate>783-581-58-22-1</Coordinate><ConfidenceRateList>-100-100-30-100</ConfidenceRateList></Entity><Entity><String>16</String><Coordinate>874-585-24-20-1</Coordinate><ConfidenceRateList>-100-100</ConfidenceRateList></Entity></Line><Line nb="29"><Entity><String>N.</String><Coordinate>1119-608-17-13-1</Coordinate><ConfidenceRateList>-30-30</ConfidenceRateList></Entity></Line><Line nb="30"><Entity><String>ez:</String><Coordinate>58-581-25-16-1</Coordinate><ConfidenceRateList>-69-30-30</ConfidenceRateList></Entity><Entity><String>:;</String><Coordinate>89-577-23-15-1</Coordinate><ConfidenceRateList>-30-69</ConfidenceRateList></Entity><Entity><String>ItemPrice</String><Coordinate>303-591-126-21-1</Coordinate><ConfidenceRateList>-100-100-100-100-100-100-100-100-100</ConfidenceRateList></Entity><Entity><String>12.00</String><Coordinate>449-598-68-21-1</Coordinate><ConfidenceRateList>-100-100-100-100-100</ConfidenceRateList></Entity><Entity><String>YouSave</String><Coordinate>578-603-98-21-1</Coordinate><ConfidenceRateList>-30-100-100-100-100-100-100</ConfidenceRateList></Entity><Entity><String>9.60</String><Coordinate>695-608-55-21-1</Coordinate><ConfidenceRateList>-100-100-100-100</ConfidenceRateList></Entity></Line><Line nb="31"><Entity><String>It</String><Coordinate>4-593-32-25-1</Coordinate><ConfidenceRateList>-30-30</ConfidenceRateList></Entity></Line><Line nb="32"><Entity><String>'i.</String><Coordinate>59-626-16-20-1</Coordinate><ConfidenceRateList>-30-30-30</ConfidenceRateList></Entity><Entity><String>4:</String><Coordinate>58-598-32-28-1</Coordinate><ConfidenceRateList>-30-30</ConfidenceRateList></Entity><Entity><String>46</String><Coordinate>138-614-16-11-1</Coordinate><ConfidenceRateList>-30-30</ConfidenceRateList></Entity><Entity><String>...</String><Coordinate>182-622-7-6-1</Coordinate><ConfidenceRateList>-30-30-30</ConfidenceRateList></Entity><Entity><String>4</String><Coordinate>207-623-23-20-1</Coordinate><ConfidenceRateList>-100</ConfidenceRateList></Entity><Entity><String>GIRLS</String><Coordinate>273-620-70-22-1</Coordinate><ConfidenceRateList>-100-100-100-100-100</ConfidenceRateList></Entity><Entity><String>LINGERIE</String><Coordinate>360-624-114-22-1</Coordinate><ConfidenceRateList>-100-100-100-100-100-100-100-100</ConfidenceRateList></Entity><Entity><String>046094525739</String><Coordinate>505-629-170-21-1</Coordinate><ConfidenceRateList>-100-100-100-100-100-100-100-100-100-100-100-100</ConfidenceRateList></Entity><Entity><String>G</String><Coordinate>708-638-11-21-1</Coordinate><ConfidenceRateList>-30</ConfidenceRateList></Entity><Entity><String>3.60</String><Coordinate>780-641-57-22-1</Coordinate><ConfidenceRateList>-100-100-100-100</ConfidenceRateList></Entity><Entity><String>16</String><Coordinate>870-644-24-21-1</Coordinate><ConfidenceRateList>-30-100</ConfidenceRateList></Entity></Line><Line nb="33"><Entity><String>'</String><Coordinate>15-627-2-3-1</Coordinate><ConfidenceRateList>-30</ConfidenceRateList></Entity><Entity><String>l</String><Coordinate>51-626-2-7-1</Coordinate><ConfidenceRateList>-30</ConfidenceRateList></Entity></Line><Line nb="34"><Entity><String>`</String><Coordinate>61-640-3-6-1</Coordinate><ConfidenceRateList>-30</ConfidenceRateList></Entity><Entity><String>e'</String><Coordinate>103-642-18-4-1</Coordinate><ConfidenceRateList>-69-30</ConfidenceRateList></Entity><Entity><String>ItemPrice</String><Coordinate>304-650-125-21-1</Coordinate><ConfidenceRateList>-100-100-100-100-100-100-100-100-100</ConfidenceRateList></Entity><Entity><String>12.00</String><Coordinate>448-656-67-21-1</Coordinate><ConfidenceRateList>-100-100-100-100-100</ConfidenceRateList></Entity><Entity><String>YouSave</String><Coordinate>576-662-98-20-1</Coordinate><ConfidenceRateList>-100-100-100-100-100-100-100</ConfidenceRateList></Entity><Entity><String>8.40</String><Coordinate>692-667-55-21-1</Coordinate><ConfidenceRateList>-100-100-100-100</ConfidenceRateList></Entity></Line><Line nb="35"><Entity><String>..</String><Coordinate>159-668-19-7-1</Coordinate><ConfidenceRateList>-30-30</ConfidenceRateList></Entity><Entity><String>.</String><Coordinate>203-668-2-3-1</Coordinate><ConfidenceRateList>-30</ConfidenceRateList></Entity></Line><Line nb="36"><Entity><String>IP(</String><Coordinate>1079-705-31-20-1</Coordinate><ConfidenceRateList>-69-30-30</ConfidenceRateList></Entity><Entity><String>•</String><Coordinate>1180-712-3-3-1</Coordinate><ConfidenceRateList>-30</ConfidenceRateList></Entity></Line><Line nb="37"><Entity><String>I.</String><Coordinate>0-676-15-10-1</Coordinate><ConfidenceRateList>-30-30</ConfidenceRateList></Entity><Entity><String>.</String><Coordinate>58-693-2-3-1</Coordinate><ConfidenceRateList>-30</ConfidenceRateList></Entity><Entity><String>0„tsto.</String><Coordinate>77-677-51-33-1</Coordinate><ConfidenceRateList>-69-69-69-69-69-30-30</ConfidenceRateList></Entity><Entity><String>ittc</String><Coordinate>143-676-24-31-1</Coordinate><ConfidenceRateList>-30-30-30-30</ConfidenceRateList></Entity><Entity><String>&gt;KIDS</String><Coordinate>275-678-69-22-1</Coordinate><ConfidenceRateList>-100-100-100-100-100</ConfidenceRateList></Entity><Entity><String>SHOES</String><Coordinate>361-681-69-22-1</Coordinate><ConfidenceRateList>-100-100-100-100-100</ConfidenceRateList></Entity><Entity><String>885177306496</String><Coordinate>503-687-170-21-1</Coordinate><ConfidenceRateList>-100-100-100-100-100-100-100-100-100-100-100-100</ConfidenceRateList></Entity><Entity><String>G</String><Coordinate>705-696-11-20-1</Coordinate><ConfidenceRateList>-30</ConfidenceRateList></Entity><Entity><String>2080</String><Coordinate>763-698-70-22-1</Coordinate><ConfidenceRateList>-100-100-100-100</ConfidenceRateList></Entity><Entity><String>.</String><Coordinate>796-717-3-4-1</Coordinate><ConfidenceRateList>-69</ConfidenceRateList></Entity><Entity><String>16</String><Coordinate>866-703-24-19-1</Coordinate><ConfidenceRateList>-100-100</ConfidenceRateList></Entity><Entity><String>:</String><Coordinate>1023-717-7-11-1</Coordinate><ConfidenceRateList>-30</ConfidenceRateList></Entity></Line><Line nb="38"><Entity><String>..</String><Coordinate>1076-736-6-4-1</Coordinate><ConfidenceRateList>-30-30</ConfidenceRateList></Entity></Line><Line nb="39"><Entity><String>ItemPrice</String><Coordinate>305-707-123-20-1</Coordinate><ConfidenceRateList>-100-100-100-100-100-100-100-100-100</ConfidenceRateList></Entity><Entity><String>52.00</String><Coordinate>446-713-68-20-1</Coordinate><ConfidenceRateList>-100-100-100-100-100</ConfidenceRateList></Entity><Entity><String>YouSave</String><Coordinate>575-720-97-20-1</Coordinate><ConfidenceRateList>-30-100-100-100-100-100-100</ConfidenceRateList></Entity><Entity><String>31.20</String><Coordinate>689-724-69-20-1</Coordinate><ConfidenceRateList>-100-100-30-100-100</ConfidenceRateList></Entity><Entity><String>.</String><Coordinate>1111-744-7-8-1</Coordinate><ConfidenceRateList>-30</ConfidenceRateList></Entity></Line><Line nb="40"><Entity><String>4</String><Coordinate>25-734-7-8-1</Coordinate><ConfidenceRateList>-69</ConfidenceRateList></Entity><Entity><String>..</String><Coordinate>34-735-7-5-1</Coordinate><ConfidenceRateList>-69-69</ConfidenceRateList></Entity><Entity><String>ihkiii■fr</String><Coordinate>105-715-75-27-1</Coordinate><ConfidenceRateList>-69-69-69-69-69-69-69-30-30</ConfidenceRateList></Entity><Entity><String>FITNESS</String><Coordinate>275-735-97-21-1</Coordinate><ConfidenceRateList>-100-100-100-100-100-100-100</ConfidenceRateList></Entity><Entity><String>DVD</String><Coordinate>389-739-40-21-1</Coordinate><ConfidenceRateList>-100-100-100</ConfidenceRateList></Entity><Entity><String>018713606358</String><Coordinate>502-744-169-20-1</Coordinate><ConfidenceRateList>-100-100-100-100-100-100-100-100-100-100-100-100</ConfidenceRateList></Entity><Entity><String>*</String><Coordinate>703-757-10-12-1</Coordinate><ConfidenceRateList>-100</ConfidenceRateList></Entity><Entity><String>8.99</String><Coordinate>775-756-55-21-1</Coordinate><ConfidenceRateList>-100-100-100-100</ConfidenceRateList></Entity><Entity><String>Ti</String><Coordinate>862-760-21-18-1</Coordinate><ConfidenceRateList>-100-30</ConfidenceRateList></Entity></Line><Line nb="41"><Entity><String>ItemPrice</String><Coordinate>305-764-122-19-1</Coordinate><ConfidenceRateList>-100-100-100-100-100-100-100-100-100</ConfidenceRateList></Entity><Entity><String>12.99</String><Coordinate>446-770-67-20-1</Coordinate><ConfidenceRateList>-100-100-100-100-100</ConfidenceRateList></Entity><Entity><String>YouSave</String><Coordinate>573-776-96-20-1</Coordinate><ConfidenceRateList>-30-100-100-100-100-100-100</ConfidenceRateList></Entity><Entity><String>4.00</String><Coordinate>687-781-54-20-1</Coordinate><ConfidenceRateList>-100-100-100-100</ConfidenceRateList></Entity></Line><Line nb="42"><Entity><String>FITNESS</String><Coordinate>275-790-97-21-1</Coordinate><ConfidenceRateList>-100-100-100-100-100-85-85</ConfidenceRateList></Entity><Entity><String>DVD</String><Coordinate>388-795-40-21-1</Coordinate><ConfidenceRateList>-100-100-100</ConfidenceRateList></Entity><Entity><String>018713589156</String><Coordinate>501-800-167-21-1</Coordinate><ConfidenceRateList>-100-100-100-100-100-100-100-100-100-100-100-100</ConfidenceRateList></Entity><Entity><String>*</String><Coordinate>700-813-11-12-1</Coordinate><ConfidenceRateList>-100</ConfidenceRateList></Entity><Entity><String>8.99</String><Coordinate>771-812-56-21-1</Coordinate><ConfidenceRateList>-100-100-100-100</ConfidenceRateList></Entity><Entity><String>T1</String><Coordinate>859-816-20-18-1</Coordinate><ConfidenceRateList>-30-30</ConfidenceRateList></Entity></Line><Line nb="43"><Entity><String>ItemPrice</String><Coordinate>305-819-121-20-1</Coordinate><ConfidenceRateList>-100-100-100-69-100-100-100-100-100</ConfidenceRateList></Entity><Entity><String>12.99</String><Coordinate>446-826-66-20-1</Coordinate><ConfidenceRateList>-100-100-100-100-100</ConfidenceRateList></Entity><Entity><String>YouSave</String><Coordinate>572-832-95-20-1</Coordinate><ConfidenceRateList>-30-100-100-100-100-100-100</ConfidenceRateList></Entity><Entity><String>4.00</String><Coordinate>684-837-54-20-1</Coordinate><ConfidenceRateList>-30-30-100-100</ConfidenceRateList></Entity><Entity><String>•</String><Coordinate>1005-849-4-5-1</Coordinate><ConfidenceRateList>-30</ConfidenceRateList></Entity><Entity><String>4.</String><Coordinate>1075-856-19-13-1</Coordinate><ConfidenceRateList>-30-30</ConfidenceRateList></Entity><Entity><String>411111/2</String><Coordinate>1132-847-64-32-1</Coordinate><ConfidenceRateList>-69-69-69-69-30-30-30-30</ConfidenceRateList></Entity></Line><Line nb="44"><Entity><String>•</String><Coordinate>0-852-5-4-1</Coordinate><ConfidenceRateList>-30</ConfidenceRateList></Entity><Entity><String>...</String><Coordinate>50-843-12-4-1</Coordinate><ConfidenceRateList>-69-69-69</ConfidenceRateList></Entity><Entity><String>7</String><Coordinate>77-841-4-18-1</Coordinate><ConfidenceRateList>-30</ConfidenceRateList></Entity><Entity><String>_v</String><Coordinate>110-854-28-18-1</Coordinate><ConfidenceRateList>-69-30</ConfidenceRateList></Entity><Entity><String>4L.</String><Coordinate>193-851-24-19-1</Coordinate><ConfidenceRateList>-69-30-30</ConfidenceRateList></Entity></Line><Line nb="45"><Entity><String>HENS</String><Coordinate>276-846-53-21-1</Coordinate><ConfidenceRateList>-30-100-100-100</ConfidenceRateList></Entity><Entity><String>RUNNING</String><Coordinate>345-849-97-21-1</Coordinate><ConfidenceRateList>-100-100-100-100-100-100-100</ConfidenceRateList></Entity><Entity><String>SH</String><Coordinate>458-854-26-21-1</Coordinate><ConfidenceRateList>-100-100</ConfidenceRateList></Entity><Entity><String>887749246261</String><Coordinate>500-856-162-20-1</Coordinate><ConfidenceRateList>-100-100-100-100-100-100-100-100-100-100-100-100</ConfidenceRateList></Entity><Entity><String>*</String><Coordinate>698-869-9-12-1</Coordinate><ConfidenceRateList>-30</ConfidenceRateList></Entity><Entity><String>44.99</String><Coordinate>755-868-69-21-1</Coordinate><ConfidenceRateList>-100-100-100-100-100</ConfidenceRateList></Entity><Entity><String>16</String><Coordinate>856-872-23-19-1</Coordinate><ConfidenceRateList>-30-100</ConfidenceRateList></Entity></Line><Line nb="46"><Entity><String>•4</String><Coordinate>11-870-17-5-1</Coordinate><ConfidenceRateList>-69-69</ConfidenceRateList></Entity><Entity><String>47</String><Coordinate>38-871-9-10-1</Coordinate><ConfidenceRateList>-69-69</ConfidenceRateList></Entity><Entity><String>e</String><Coordinate>55-855-37-40-1</Coordinate><ConfidenceRateList>-30</ConfidenceRateList></Entity><Entity><String>14</String><Coordinate>107-864-22-27-1</Coordinate><ConfidenceRateList>-30-30</ConfidenceRateList></Entity><Entity><String>4</String><Coordinate>149-875-4-7-1</Coordinate><ConfidenceRateList>-30</ConfidenceRateList></Entity><Entity><String>'</String><Coordinate>176-883-2-2-1</Coordinate><ConfidenceRateList>-30</ConfidenceRateList></Entity><Entity><String>ItemPrice</String><Coordinate>305-875-121-19-1</Coordinate><ConfidenceRateList>-100-100-100-100-100-100-30-100-100</ConfidenceRateList></Entity><Entity><String>59.99</String><Coordinate>443-880-67-20-1</Coordinate><ConfidenceRateList>-100-100-30-100-100</ConfidenceRateList></Entity><Entity><String>YouSave</String><Coordinate>570-888-95-20-1</Coordinate><ConfidenceRateList>-100-100-100-30-100-30-100</ConfidenceRateList></Entity><Entity><String>15.00</String><Coordinate>684-892-66-20-1</Coordinate><ConfidenceRateList>-100-100-100-100-100</ConfidenceRateList></Entity><Entity><String>r</String><Coordinate>940-912-10-15-1</Coordinate><ConfidenceRateList>-30</ConfidenceRateList></Entity><Entity><String>r</String><Coordinate>1043-906-14-9-1</Coordinate><ConfidenceRateList>-30</ConfidenceRateList></Entity></Line><Line nb="47"><Entity><String>'tor</String><Coordinate>125-898-27-19-1</Coordinate><ConfidenceRateList>-30-85-30-30</ConfidenceRateList></Entity><Entity><String>.</String><Coordinate>169-923-1-2-1</Coordinate><ConfidenceRateList>-100</ConfidenceRateList></Entity><Entity><String>..</String><Coordinate>183-907-6-3-1</Coordinate><ConfidenceRateList>-30-30</ConfidenceRateList></Entity><Entity><String>_</String><Coordinate>219-924-2-1-1</Coordinate><ConfidenceRateList>-30</ConfidenceRateList></Entity><Entity><String>HENS</String><Coordinate>276-901-52-21-1</Coordinate><ConfidenceRateList>-30-100-100-100</ConfidenceRateList></Entity><Entity><String>TEK</String><Coordinate>345-905-39-20-1</Coordinate><ConfidenceRateList>-100-100-100</ConfidenceRateList></Entity><Entity><String>GEAR</String><Coordinate>401-907-54-20-1</Coordinate><ConfidenceRateList>-100-100-100-100</ConfidenceRateList></Entity><Entity><String>400951675300</String><Coordinate>499-911-165-20-1</Coordinate><ConfidenceRateList>-100-100-100-100-100-100-100-100-100-100-100-100</ConfidenceRateList></Entity><Entity><String>*</String><Coordinate>696-925-10-12-1</Coordinate><ConfidenceRateList>-100</ConfidenceRateList></Entity><Entity><String>9.60</String><Coordinate>766-924-55-21-1</Coordinate><ConfidenceRateList>-100-100-100-100</ConfidenceRateList></Entity><Entity><String>16</String><Coordinate>852-928-24-19-1</Coordinate><ConfidenceRateList>-30-100</ConfidenceRateList></Entity></Line><Line nb="48"><Entity><String>IA■</String><Coordinate>129-927-32-9-1</Coordinate><ConfidenceRateList>-69-30-30</ConfidenceRateList></Entity><Entity><String>4</String><Coordinate>181-927-19-18-1</Coordinate><ConfidenceRateList>-85</ConfidenceRateList></Entity><Entity><String>IfemPrice</String><Coordinate>304-930-121-19-1</Coordinate><ConfidenceRateList>-100-30-100-69-100-100-100-100-100</ConfidenceRateList></Entity><Entity><String>24.00</String><Coordinate>443-936-66-20-1</Coordinate><ConfidenceRateList>-100-100-100-100-100</ConfidenceRateList></Entity><Entity><String>YouSave</String><Coordinate>568-942-95-19-1</Coordinate><ConfidenceRateList>-30-100-100-100-100-100-100</ConfidenceRateList></Entity><Entity><String>14.40</String><Coordinate>682-948-66-19-1</Coordinate><ConfidenceRateList>-100-100-100-100-100</ConfidenceRateList></Entity><Entity><String>.</String><Coordinate>1056-973-11-6-1</Coordinate><ConfidenceRateList>-30</ConfidenceRateList></Entity></Line><Line nb="49"><Entity><String>•alr</String><Coordinate>153-943-30-12-1</Coordinate><ConfidenceRateList>-30-69-69-30</ConfidenceRateList></Entity><Entity><String>.</String><Coordinate>214-950-2-2-1</Coordinate><ConfidenceRateList>-30</ConfidenceRateList></Entity></Line><Line nb="50"><Entity><String>•</String><Coordinate>49-951-3-3-1</Coordinate><ConfidenceRateList>-30</ConfidenceRateList></Entity><Entity><String>1</String><Coordinate>123-955-4-4-1</Coordinate><ConfidenceRateList>-30</ConfidenceRateList></Entity><Entity><String>..v..</String><Coordinate>140-955-24-10-1</Coordinate><ConfidenceRateList>-69-69-69-30-30</ConfidenceRateList></Entity><Entity><String>.</String><Coordinate>186-970-2-2-1</Coordinate><ConfidenceRateList>-30</ConfidenceRateList></Entity><Entity><String>:</String><Coordinate>199-957-9-16-1</Coordinate><ConfidenceRateList>-30</ConfidenceRateList></Entity><Entity><String>r!sx</String><Coordinate>226-960-29-9-1</Coordinate><ConfidenceRateList>-69-69-30-30</ConfidenceRateList></Entity><Entity><String>BASIC</String><Coordinate>275-957-67-21-1</Coordinate><ConfidenceRateList>-100-100-100-100-100</ConfidenceRateList></Entity><Entity><String>TEES</String><Coordinate>359-960-53-20-1</Coordinate><ConfidenceRateList>-100-100-100-100</ConfidenceRateList></Entity></Line><Line nb="51"><Entity><String>•</String><Coordinate>54-971-2-1-1</Coordinate><ConfidenceRateList>-30</ConfidenceRateList></Entity><Entity><String>I</String><Coordinate>123-964-21-21-1</Coordinate><ConfidenceRateList>-30</ConfidenceRateList></Entity><Entity><String>.</String><Coordinate>154-981-1-2-1</Coordinate><ConfidenceRateList>-69</ConfidenceRateList></Entity><Entity><String>4$</String><Coordinate>161-974-14-8-1</Coordinate><ConfidenceRateList>-69-69</ConfidenceRateList></Entity></Line><Line nb="52"><Entity><String>a</String><Coordinate>175-983-10-5-1</Coordinate><ConfidenceRateList>-100</ConfidenceRateList></Entity><Entity><String>ItemPrice</String><Coordinate>304-985-120-20-1</Coordinate><ConfidenceRateList>-100-100-100-100-100-100-100-100-100</ConfidenceRateList></Entity><Entity><String>22.487714M</String><Coordinate>441-966-221-50-1</Coordinate><ConfidenceRateList>-100-100-85-30-100-100-100-69-100-69</ConfidenceRateList></Entity><Entity><String>.1</String><Coordinate>679-1003-6-18-1</Coordinate><ConfidenceRateList>-30-85</ConfidenceRateList></Entity><Entity><String>80</String><Coordinate>720-1005-25-20-1</Coordinate><ConfidenceRateList>-100-100</ConfidenceRateList></Entity><Entity><String>2.20</String><Coordinate>763-980-55-21-1</Coordinate><ConfidenceRateList>-100-100-100-100</ConfidenceRateList></Entity><Entity><String>16</String><Coordinate>849-983-24-19-1</Coordinate><ConfidenceRateList>-30-100</ConfidenceRateList></Entity><Entity><String>[</String><Coordinate>935-989-8-25-1</Coordinate><ConfidenceRateList>-30</ConfidenceRateList></Entity><Entity><String>_</String><Coordinate>998-1015-10-2-1</Coordinate><ConfidenceRateList>-30</ConfidenceRateList></Entity></Line><Line nb="53"><Entity><String>•</String><Coordinate>253-1012-1-1-1</Coordinate><ConfidenceRateList>-30</ConfidenceRateList></Entity><Entity><String>le</String><Coordinate>936-1030-25-12-1</Coordinate><ConfidenceRateList>-30-30</ConfidenceRateList></Entity><Entity><String>.</String><Coordinate>969-1053-2-2-1</Coordinate><ConfidenceRateList>-30</ConfidenceRateList></Entity><Entity><String>Air</String><Coordinate>973-1035-23-10-1</Coordinate><ConfidenceRateList>-69-30-30</ConfidenceRateList></Entity><Entity><String>0</String><Coordinate>997-1017-17-22-1</Coordinate><ConfidenceRateList>-100</ConfidenceRateList></Entity><Entity><String>111fr</String><Coordinate>1031-1015-58-46-1</Coordinate><ConfidenceRateList>-30-69-69-30-30</ConfidenceRateList></Entity></Line><Line nb="54"><Entity><String>.</String><Coordinate>141-1011-1-2-1</Coordinate><ConfidenceRateList>-30</ConfidenceRateList></Entity><Entity><String>.</String><Coordinate>163-1013-3-3-1</Coordinate><ConfidenceRateList>-30</ConfidenceRateList></Entity></Line><Line nb="55"><Entity><String>64</String><Coordinate>275-1011-25-20-1</Coordinate><ConfidenceRateList>-30-100</ConfidenceRateList></Entity><Entity><String>6X</String><Coordinate>316-1014-25-20-1</Coordinate><ConfidenceRateList>-100-100</ConfidenceRateList></Entity><Entity><String>TOPS</String><Coordinate>358-1015-53-19-1</Coordinate><ConfidenceRateList>-100-100-100-100</ConfidenceRateList></Entity><Entity><String>400952684097</String><Coordinate>496-1021-164-19-1</Coordinate><ConfidenceRateList>-100-100-100-100-100-100-100-100-100-100-100-100</ConfidenceRateList></Entity><Entity><String>G</String><Coordinate>690-1031-12-18-1</Coordinate><ConfidenceRateList>-30</ConfidenceRateList></Entity><Entity><String>6.00</String><Coordinate>761-1035-54-20-1</Coordinate><ConfidenceRateList>-100-100-100-100</ConfidenceRateList></Entity><Entity><String>16</String><Coordinate>847-1039-23-19-1</Coordinate><ConfidenceRateList>-30-100</ConfidenceRateList></Entity><Entity><String>*1</String><Coordinate>954-1054-9-5-1</Coordinate><ConfidenceRateList>-30-30</ConfidenceRateList></Entity><Entity><String>r</String><Coordinate>1026-1057-3-5-1</Coordinate><ConfidenceRateList>-30</ConfidenceRateList></Entity></Line><Line nb="56"><Entity><String>ir</String><Coordinate>111-1021-16-11-1</Coordinate><ConfidenceRateList>-30-30</ConfidenceRateList></Entity><Entity><String>I</String><Coordinate>144-1024-5-12-1</Coordinate><ConfidenceRateList>-30</ConfidenceRateList></Entity><Entity><String>*ii</String><Coordinate>235-1028-19-13-1</Coordinate><ConfidenceRateList>-30-30-30</ConfidenceRateList></Entity></Line><Line nb="57"><Entity><String>wir</String><Coordinate>951-1066-12-10-1</Coordinate><ConfidenceRateList>-69-30-30</ConfidenceRateList></Entity><Entity><String>•</String><Coordinate>1032-1070-1-2-1</Coordinate><ConfidenceRateList>-30</ConfidenceRateList></Entity><Entity><String>ale</String><Coordinate>1042-1064-24-13-1</Coordinate><ConfidenceRateList>-69-30-30</ConfidenceRateList></Entity></Line><Line nb="58"><Entity><String>Artrir:1</String><Coordinate>16-1024-109-53-1</Coordinate><ConfidenceRateList>-69-69-69-30-30-69-30-30</ConfidenceRateList></Entity><Entity><String>IfemPrice</String><Coordinate>303-1039-120-19-1</Coordinate><ConfidenceRateList>-100-30-100-100-100-100-100-100-100</ConfidenceRateList></Entity><Entity><String>20.00</String><Coordinate>440-1045-66-20-1</Coordinate><ConfidenceRateList>-100-100-100-100-100</ConfidenceRateList></Entity><Entity><String>YouSave</String><Coordinate>565-1051-93-20-1</Coordinate><ConfidenceRateList>-30-100-100-100-100-100-100</ConfidenceRateList></Entity><Entity><String>14.00</String><Coordinate>677-1057-65-19-1</Coordinate><ConfidenceRateList>-100-100-100-100-100</ConfidenceRateList></Entity></Line><Line nb="59"><Entity><String>Alit</String><Coordinate>21-1055-31-21-1</Coordinate><ConfidenceRateList>-69-69-30-30</ConfidenceRateList></Entity><Entity><String>•</String><Coordinate>64-1071-1-0-1</Coordinate><ConfidenceRateList>-30</ConfidenceRateList></Entity><Entity><String>%</String><Coordinate>93-1060-5-6-1</Coordinate><ConfidenceRateList>-30</ConfidenceRateList></Entity><Entity><String>'Iw.</String><Coordinate>165-1060-20-8-1</Coordinate><ConfidenceRateList>-69-30-30-30</ConfidenceRateList></Entity><Entity><String>.</String><Coordinate>215-1081-2-2-1</Coordinate><ConfidenceRateList>-30</ConfidenceRateList></Entity><Entity><String>GIRLS</String><Coordinate>274-1065-66-20-1</Coordinate><ConfidenceRateList>-100-100-100-100-100</ConfidenceRateList></Entity><Entity><String>SLEEPWEAR</String><Coordinate>357-1069-122-20-1</Coordinate><ConfidenceRateList>-100-100-100-100-100-100-100-100-100</ConfidenceRateList></Entity><Entity><String>886166719716</String><Coordinate>495-1074-162-19-1</Coordinate><ConfidenceRateList>-100-100-100-100-100-100-100-100-100-100-100-100</ConfidenceRateList></Entity><Entity><String>G</String><Coordinate>688-1084-11-19-1</Coordinate><ConfidenceRateList>-30</ConfidenceRateList></Entity><Entity><String>10.50</String><Coordinate>746-1088-66-20-1</Coordinate><ConfidenceRateList>-100-100-100-100-100</ConfidenceRateList></Entity><Entity><String>16</String><Coordinate>844-1093-23-19-1</Coordinate><ConfidenceRateList>-30-100</ConfidenceRateList></Entity></Line><Line nb="60"><Entity><String>ItemPrice</String><Coordinate>302-1093-120-19-1</Coordinate><ConfidenceRateList>-100-100-100-69-100-100-30-100-100</ConfidenceRateList></Entity><Entity><String>35.00</String><Coordinate>439-1098-66-19-1</Coordinate><ConfidenceRateList>-100-100-30-100-100</ConfidenceRateList></Entity><Entity><String>YouSave</String><Coordinate>564-1104-92-19-1</Coordinate><ConfidenceRateList>-30-100-100-100-100-100-100</ConfidenceRateList></Entity><Entity><String>24.50</String><Coordinate>673-1110-67-19-1</Coordinate><ConfidenceRateList>-100-100-30-100-100</ConfidenceRateList></Entity></Line><Line nb="61"><Entity><String>BOYS</String><Coordinate>274-1118-52-20-1</Coordinate><ConfidenceRateList>-100-100-100-100</ConfidenceRateList></Entity><Entity><String>L/S</String><Coordinate>342-1122-39-19-1</Coordinate><ConfidenceRateList>-100-100-100</ConfidenceRateList></Entity><Entity><String>TEES</String><Coordinate>397-1124-52-20-1</Coordinate><ConfidenceRateList>-100-100-100-100</ConfidenceRateList></Entity><Entity><String>400951884887</String><Coordinate>493-1128-163-19-1</Coordinate><ConfidenceRateList>-100-100-100-100-100-100-100-100-100-100-100-100</ConfidenceRateList></Entity><Entity><String>G</String><Coordinate>686-1137-11-19-1</Coordinate><ConfidenceRateList>-30</ConfidenceRateList></Entity><Entity><String>7.50</String><Coordinate>757-1141-52-19-1</Coordinate><ConfidenceRateList>-100-100-100-100</ConfidenceRateList></Entity><Entity><String>16</String><Coordinate>840-1146-24-17-1</Coordinate><ConfidenceRateList>-100-100</ConfidenceRateList></Entity></Line><Line nb="62"><Entity><String>4.</String><Coordinate>19-1140-25-16-1</Coordinate><ConfidenceRateList>-100-30</ConfidenceRateList></Entity><Entity><String>.</String><Coordinate>61-1150-1-2-1</Coordinate><ConfidenceRateList>-100</ConfidenceRateList></Entity><Entity><String>ItemPrice</String><Coordinate>302-1146-119-19-1</Coordinate><ConfidenceRateList>-100-100-100-100-100-100-100-100-100</ConfidenceRateList></Entity><Entity><String>25.00</String><Coordinate>437-1152-66-19-1</Coordinate><ConfidenceRateList>-100-100-100-100-100</ConfidenceRateList></Entity><Entity><String>YouSave</String><Coordinate>562-1157-92-18-1</Coordinate><ConfidenceRateList>-100-100-100-100-100-30-100</ConfidenceRateList></Entity><Entity><String>17.50</String><Coordinate>674-1164-63-19-1</Coordinate><ConfidenceRateList>-100-100-100-100-100</ConfidenceRateList></Entity></Line><Line nb="63"><Entity><String>.40.</String><Coordinate>206-1133-28-12-1</Coordinate><ConfidenceRateList>-69-30-30-30</ConfidenceRateList></Entity><Entity><String>4s</String><Coordinate>1025-1164-10-10-1</Coordinate><ConfidenceRateList>-30-30</ConfidenceRateList></Entity></Line><Line nb="64"><Entity><String>.</String><Coordinate>16-1172-1-2-1</Coordinate><ConfidenceRateList>-30</ConfidenceRateList></Entity><Entity><String>Ir</String><Coordinate>120-1173-10-8-1</Coordinate><ConfidenceRateList>-30-100</ConfidenceRateList></Entity><Entity><String>'</String><Coordinate>135-1170-1-4-1</Coordinate><ConfidenceRateList>-30</ConfidenceRateList></Entity><Entity><String>II.</String><Coordinate>164-1172-13-10-1</Coordinate><ConfidenceRateList>-69-69-30</ConfidenceRateList></Entity><Entity><String>•</String><Coordinate>193-1175-1-1-1</Coordinate><ConfidenceRateList>-30</ConfidenceRateList></Entity><Entity><String>BOYS</String><Coordinate>273-1171-52-20-1</Coordinate><ConfidenceRateList>-100-100-100-100</ConfidenceRateList></Entity><Entity><String>L/S</String><Coordinate>341-1175-39-20-1</Coordinate><ConfidenceRateList>-100-100-100</ConfidenceRateList></Entity><Entity><String>KNITS</String><Coordinate>396-1177-66-20-1</Coordinate><ConfidenceRateList>-100-100-100-100-100</ConfidenceRateList></Entity><Entity><String>887219295133</String><Coordinate>492-1180-161-19-1</Coordinate><ConfidenceRateList>-100-100-100-100-100-100-100-100-100-100-100-100</ConfidenceRateList></Entity><Entity><String>G</String><Coordinate>684-1190-11-19-1</Coordinate><ConfidenceRateList>-30</ConfidenceRateList></Entity><Entity><String>10.00</String><Coordinate>741-1194-66-20-1</Coordinate><ConfidenceRateList>-100-100-100-100-100</ConfidenceRateList></Entity><Entity><String>16</String><Coordinate>838-1199-23-18-1</Coordinate><ConfidenceRateList>-30-100</ConfidenceRateList></Entity></Line><Line nb="65"><Entity><String>1</String><Coordinate>191-1194-10-13-1</Coordinate><ConfidenceRateList>-30</ConfidenceRateList></Entity><Entity><String>.</String><Coordinate>236-1206-1-1-1</Coordinate><ConfidenceRateList>-30</ConfidenceRateList></Entity><Entity><String>ItemPrice</String><Coordinate>301-1199-119-18-1</Coordinate><ConfidenceRateList>-100-100-100-100-100-100-100-100-100</ConfidenceRateList></Entity><Entity><String>25</String><Coordinate>436-1204-25-19-1</Coordinate><ConfidenceRateList>-85-85</ConfidenceRateList></Entity><Entity><String>'</String><Coordinate>468-1222-2-2-1</Coordinate><ConfidenceRateList>-30</ConfidenceRateList></Entity><Entity><String>00</String><Coordinate>477-1207-25-18-1</Coordinate><ConfidenceRateList>-100-100</ConfidenceRateList></Entity><Entity><String>YouSave</String><Coordinate>560-1210-92-19-1</Coordinate><ConfidenceRateList>-30-100-100-100-100-100-100</ConfidenceRateList></Entity><Entity><String>15</String><Coordinate>671-1217-23-19-1</Coordinate><ConfidenceRateList>-85-85</ConfidenceRateList></Entity><Entity><String>00</String><Coordinate>710-1219-25-19-1</Coordinate><ConfidenceRateList>-100-100</ConfidenceRateList></Entity></Line><Line nb="66"><Entity><String>4</String><Coordinate>148-1235-6-7-1</Coordinate><ConfidenceRateList>-30</ConfidenceRateList></Entity><Entity><String>4#</String><Coordinate>196-1215-19-12-1</Coordinate><ConfidenceRateList>-30-30</ConfidenceRateList></Entity><Entity><String>MISSES</String><Coordinate>272-1224-80-20-1</Coordinate><ConfidenceRateList>-100-100-100-100-100-100</ConfidenceRateList></Entity><Entity><String>TOPS</String><Coordinate>368-1228-52-20-1</Coordinate><ConfidenceRateList>-100-100-100-100</ConfidenceRateList></Entity><Entity><String>884094832010</String><Coordinate>490-1233-161-19-1</Coordinate><ConfidenceRateList>-100-100-30-100-100-100-100-100-100-100-100-100</ConfidenceRateList></Entity><Entity><String>G</String><Coordinate>682-1244-10-18-1</Coordinate><ConfidenceRateList>-30</ConfidenceRateList></Entity><Entity><String>11.80</String><Coordinate>738-1247-66-20-1</Coordinate><ConfidenceRateList>-100-100-100-100-100</ConfidenceRateList></Entity><Entity><String>T6</String><Coordinate>836-1253-22-17-1</Coordinate><ConfidenceRateList>-100-100</ConfidenceRateList></Entity></Line><Line nb="67"><Entity><String>.</String><Coordinate>9-1236-12-9-1</Coordinate><ConfidenceRateList>-30</ConfidenceRateList></Entity><Entity><String>Ab‘</String><Coordinate>66-1234-14-7-1</Coordinate><ConfidenceRateList>-30-30-30</ConfidenceRateList></Entity><Entity><String>'</String><Coordinate>125-1238-1-5-1</Coordinate><ConfidenceRateList>-30</ConfidenceRateList></Entity><Entity><String>:</String><Coordinate>162-1241-6-11-1</Coordinate><ConfidenceRateList>-30</ConfidenceRateList></Entity><Entity><String>_</String><Coordinate>207-1252-3-0-1</Coordinate><ConfidenceRateList>-30</ConfidenceRateList></Entity></Line><Line nb="68"><Entity><String>•</String><Coordinate>8-1245-3-4-1</Coordinate><ConfidenceRateList>-30</ConfidenceRateList></Entity><Entity><String>.</String><Coordinate>21-1265-3-2-1</Coordinate><ConfidenceRateList>-30</ConfidenceRateList></Entity><Entity><String>Is</String><Coordinate>48-1244-12-13-1</Coordinate><ConfidenceRateList>-30-30</ConfidenceRateList></Entity></Line><Line nb="69"><Entity><String>ItemPrice</String><Coordinate>301-1251-118-19-1</Coordinate><ConfidenceRateList>-100-100-100-100-100-100-100-100-100</ConfidenceRateList></Entity><Entity><String>59.00</String><Coordinate>435-1257-65-18-1</Coordinate><ConfidenceRateList>-100-100-100-100-100</ConfidenceRateList></Entity><Entity><String>YouSave</String><Coordinate>558-1264-92-18-1</Coordinate><ConfidenceRateList>-30-100-100-100-100-100-100</ConfidenceRateList></Entity><Entity><String>17.20</String><Coordinate>667-1269-66-18-1</Coordinate><ConfidenceRateList>-100-100-100-100-100</ConfidenceRateList></Entity></Line><Line nb="70"><Entity><String>'</String><Coordinate>130-1289-2-3-1</Coordinate><ConfidenceRateList>-30</ConfidenceRateList></Entity><Entity><String>A</String><Coordinate>155-1272-41-36-1</Coordinate><ConfidenceRateList>-30</ConfidenceRateList></Entity></Line><Line nb="71"><Entity><String>HENS</String><Coordinate>272-1276-53-19-1</Coordinate><ConfidenceRateList>-30-100-100-100</ConfidenceRateList></Entity><Entity><String>DRESS</String><Coordinate>340-1278-66-19-1</Coordinate><ConfidenceRateList>-100-100-100-100-100</ConfidenceRateList></Entity><Entity><String>SHIR</String><Coordinate>422-1282-52-19-1</Coordinate><ConfidenceRateList>-100-100-100-100</ConfidenceRateList></Entity><Entity><String>631712006051</String><Coordinate>489-1285-156-18-1</Coordinate><ConfidenceRateList>-100-100-100-100-100-100-100-100-100-100-100-100</ConfidenceRateList></Entity><Entity><String>G</String><Coordinate>680-1295-11-18-1</Coordinate><ConfidenceRateList>-30</ConfidenceRateList></Entity><Entity><String>9.00</String><Coordinate>749-1300-52-19-1</Coordinate><ConfidenceRateList>-100-100-100-100</ConfidenceRateList></Entity><Entity><String>16</String><Coordinate>832-1305-24-18-1</Coordinate><ConfidenceRateList>-100-100</ConfidenceRateList></Entity></Line><Line nb="72"><Entity><String>libio</String><Coordinate>20-1299-34-26-1</Coordinate><ConfidenceRateList>-69-69-69-30-30</ConfidenceRateList></Entity><Entity><String>ItemPrice</String><Coordinate>301-1302-117-18-1</Coordinate><ConfidenceRateList>-100-100-100-100-100-100-30-100-100</ConfidenceRateList></Entity><Entity><String>15.00</String><Coordinate>435-1309-64-18-1</Coordinate><ConfidenceRateList>-100-100-100-100-100</ConfidenceRateList></Entity><Entity><String>YouSave</String><Coordinate>557-1314-91-18-1</Coordinate><ConfidenceRateList>-30-100-100-100-100-100-100</ConfidenceRateList></Entity><Entity><String>36.00</String><Coordinate>665-1320-65-19-1</Coordinate><ConfidenceRateList>-100-100-100-100-100</ConfidenceRateList></Entity></Line><Line nb="73"><Entity><String>SUBTOTAL</String><Coordinate>555-1368-105-19-1</Coordinate><ConfidenceRateList>-100-100-100-100-100-100-100-100</ConfidenceRateList></Entity><Entity><String>167.56</String><Coordinate>719-1377-77-19-1</Coordinate><ConfidenceRateList>-100-100-100-100-100-100</ConfidenceRateList></Entity></Line><Line nb="74"><Entity><String>4</String><Coordinate>6-1362-13-9-1</Coordinate><ConfidenceRateList>-30</ConfidenceRateList></Entity></Line><Line nb="75"><Entity><String>.</String><Coordinate>67-1392-1-1-1</Coordinate><ConfidenceRateList>-30</ConfidenceRateList></Entity><Entity><String>ui.</String><Coordinate>115-1380-15-13-1</Coordinate><ConfidenceRateList>-69-30-30</ConfidenceRateList></Entity><Entity><String>MUSE</String><Coordinate>297-1382-51-19-1</Coordinate><ConfidenceRateList>-100-100-100-100</ConfidenceRateList></Entity><Entity><String>SUBJECT</String><Coordinate>365-1385-91-19-1</Coordinate><ConfidenceRateList>-100-100-100-100-100-100-100</ConfidenceRateList></Entity><Entity><String>TO</String><Coordinate>473-1389-24-19-1</Coordinate><ConfidenceRateList>-100-100</ConfidenceRateList></Entity><Entity><String>DSC</String><Coordinate>513-1391-38-20-1</Coordinate><ConfidenceRateList>-30-100-100</ConfidenceRateList></Entity><Entity><String>167.56</String><Coordinate>609-1398-77-19-1</Coordinate><ConfidenceRateList>-100-100-100-30-100-100</ConfidenceRateList></Entity></Line><Line nb="76"><Entity><String>KOHL'S</String><Coordinate>296-1408-78-19-1</Coordinate><ConfidenceRateList>-100-100-100-100-100-100</ConfidenceRateList></Entity><Entity><String>CASH</String><Coordinate>390-1413-52-19-1</Coordinate><ConfidenceRateList>-100-100-100-100</ConfidenceRateList></Entity><Entity><String>167828036939521</String><Coordinate>460-1416-194-19-1</Coordinate><ConfidenceRateList>-100-100-100-100-100-100-100-100-100-100-100-100-100-100-100</ConfidenceRateList></Entity><Entity><String>5.00</String><Coordinate>743-1431-51-19-1</Coordinate><ConfidenceRateList>-100-100-100-100</ConfidenceRateList></Entity></Line><Line nb="77"><Entity><String>0</String><Coordinate>123-1438-4-4-1</Coordinate><ConfidenceRateList>-30</ConfidenceRateList></Entity></Line><Line nb="78"><Entity><String>.</String><Coordinate>1059-1456-3-3-1</Coordinate><ConfidenceRateList>-30</ConfidenceRateList></Entity><Entity><String>Aript</String><Coordinate>1080-1432-71-41-1</Coordinate><ConfidenceRateList>-69-69-69-30-30</ConfidenceRateList></Entity></Line><Line nb="79"><Entity><String>•</String><Coordinate>7-1455-1-1-1</Coordinate><ConfidenceRateList>-30</ConfidenceRateList></Entity><Entity><String>i.</String><Coordinate>205-1432-10-11-1</Coordinate><ConfidenceRateList>-30-30</ConfidenceRateList></Entity><Entity><String>**REMAINING</String><Coordinate>296-1436-144-19-1</Coordinate><ConfidenceRateList>-100-100-100-100-100-100-100-100-100-100-100</ConfidenceRateList></Entity><Entity><String>BALANCE</String><Coordinate>457-1442-92-19-1</Coordinate><ConfidenceRateList>-100-100-100-100-100-100-100</ConfidenceRateList></Entity><Entity><String>0.00</String><Coordinate>606-1450-51-19-1</Coordinate><ConfidenceRateList>-100-100-100-100</ConfidenceRateList></Entity></Line><Line nb="80"><Entity><String>.).</String><Coordinate>48-1434-16-7-1</Coordinate><ConfidenceRateList>-30-30-30</ConfidenceRateList></Entity><Entity><String>.:</String><Coordinate>109-1438-14-16-1</Coordinate><ConfidenceRateList>-69-69</ConfidenceRateList></Entity></Line><Line nb="81"><Entity><String>MDSE</String><Coordinate>295-1461-50-18-1</Coordinate><ConfidenceRateList>-100-30-100-100</ConfidenceRateList></Entity><Entity><String>SUBJECT</String><Coordinate>362-1464-91-19-1</Coordinate><ConfidenceRateList>-100-100-100-100-100-100-100</ConfidenceRateList></Entity><Entity><String>TO</String><Coordinate>471-1469-23-18-1</Coordinate><ConfidenceRateList>-100-100</ConfidenceRateList></Entity><Entity><String>DSC</String><Coordinate>510-1471-38-19-1</Coordinate><ConfidenceRateList>-30-100-100</ConfidenceRateList></Entity><Entity><String>112.39</String><Coordinate>607-1476-76-19-1</Coordinate><ConfidenceRateList>-100-100-100-30-100-100</ConfidenceRateList></Entity></Line><Line nb="82"><Entity><String>$</String><Coordinate>268-1487-10-15-1</Coordinate><ConfidenceRateList>-100</ConfidenceRateList></Entity><Entity><String>TRANSACTION</String><Coordinate>295-1487-144-18-1</Coordinate><ConfidenceRateList>-30-100-100-100-100-100-100-30-100-100-100</ConfidenceRateList></Entity><Entity><String>DISCOUNT</String><Coordinate>456-1495-104-19-1</Coordinate><ConfidenceRateList>-100-100-100-100-100-100-100-100</ConfidenceRateList></Entity><Entity><String>10.00</String><Coordinate>728-1509-63-19-1</Coordinate><ConfidenceRateList>-100-100-100-100-100</ConfidenceRateList></Entity></Line><Line nb="83"><Entity><String>MUSE</String><Coordinate>294-1513-50-18-1</Coordinate><ConfidenceRateList>-100-100-100-100</ConfidenceRateList></Entity><Entity><String>SUBJECT</String><Coordinate>361-1515-90-18-1</Coordinate><ConfidenceRateList>-100-100-100-100-100-100-100</ConfidenceRateList></Entity><Entity><String>TO</String><Coordinate>470-1521-22-17-1</Coordinate><ConfidenceRateList>-100-100</ConfidenceRateList></Entity><Entity><String>DSC</String><Coordinate>509-1523-37-18-1</Coordinate><ConfidenceRateList>-30-100-100</ConfidenceRateList></Entity><Entity><String>132.39</String><Coordinate>604-1528-77-18-1</Coordinate><ConfidenceRateList>-100-100-100-100-100-100</ConfidenceRateList></Entity></Line><Line nb="84"><Entity><String>.</String><Coordinate>922-1558-2-2-1</Coordinate><ConfidenceRateList>-30</ConfidenceRateList></Entity><Entity><String>•4.</String><Coordinate>1010-1556-13-2-1</Coordinate><ConfidenceRateList>-69-30-100</ConfidenceRateList></Entity><Entity><String>...</String><Coordinate>1039-1554-10-14-1</Coordinate><ConfidenceRateList>-30-30-30</ConfidenceRateList></Entity></Line><Line nb="85"><Entity><String>%</String><Coordinate>267-1537-10-15-1</Coordinate><ConfidenceRateList>-69</ConfidenceRateList></Entity><Entity><String>TRANSACTION</String><Coordinate>294-1537-143-18-1</Coordinate><ConfidenceRateList>-100-100-100-100-100-100-100-100-100-100-100</ConfidenceRateList></Entity><Entity><String>DISCOUNT</String><Coordinate>454-1545-104-18-1</Coordinate><ConfidenceRateList>-100-100-100-100-100-100-100-100</ConfidenceRateList></Entity><Entity><String>30x</String><Coordinate>575-1552-37-18-1</Coordinate><ConfidenceRateList>-100-100-69</ConfidenceRateList></Entity><Entity><String>39.72</String><Coordinate>723-1559-65-18-1</Coordinate><ConfidenceRateList>-85-85-30-100-100</ConfidenceRateList></Entity><Entity><String>.„</String><Coordinate>1179-1581-20-5-1</Coordinate><ConfidenceRateList>-30-30</ConfidenceRateList></Entity></Line><Line nb="86"><Entity><String>int</String><Coordinate>1018-1592-17-8-1</Coordinate><ConfidenceRateList>-69-30-30</ConfidenceRateList></Entity><Entity><String>ar</String><Coordinate>1084-1586-27-14-1</Coordinate><ConfidenceRateList>-30-30</ConfidenceRateList></Entity><Entity><String>.i.</String><Coordinate>1121-1587-10-13-1</Coordinate><ConfidenceRateList>-69-30-30</ConfidenceRateList></Entity><Entity><String>:__</String><Coordinate>1143-1589-14-11-1</Coordinate><ConfidenceRateList>-69-30-30</ConfidenceRateList></Entity><Entity><String>•</String><Coordinate>1181-1586-19-14-1</Coordinate><ConfidenceRateList>-30</ConfidenceRateList></Entity></Line><Line nb="87"><Entity><String>11=</String><Coordinate>295-1561-34-16-1</Coordinate><ConfidenceRateList>-30-100-100</ConfidenceRateList></Entity><Entity><String>13.84</String><Coordinate>388-1567-63-17-1</Coordinate><ConfidenceRateList>-100-100-100-100-100</ConfidenceRateList></Entity><Entity><String>@</String><Coordinate>467-1571-10-17-1</Coordinate><ConfidenceRateList>-100</ConfidenceRateList></Entity><Entity><String>6.0%</String><Coordinate>494-1572-50-17-1</Coordinate><ConfidenceRateList>-100-100-30-69</ConfidenceRateList></Entity><Entity><String>TAX</String><Coordinate>615-1578-37-17-1</Coordinate><ConfidenceRateList>-100-100-100</ConfidenceRateList></Entity><Entity><String>0</String><Coordinate>735-1585-11-15-1</Coordinate><ConfidenceRateList>-100</ConfidenceRateList></Entity><Entity><String>R3</String><Coordinate>762-1586-24-14-1</Coordinate><ConfidenceRateList>-85-30</ConfidenceRateList></Entity><Entity><String>.</String><Coordinate>931-1597-3-3-1</Coordinate><ConfidenceRateList>-30</ConfidenceRateList></Entity></Line><Line nb="88"><Entity><String>n</String><Coordinate>467-1595-9-5-1</Coordinate><ConfidenceRateList>-100</ConfidenceRateList></Entity><Entity><String>a</String><Coordinate>494-1596-9-4-1</Coordinate><ConfidenceRateList>-100</ConfidenceRateList></Entity><Entity><String>_</String><Coordinate>522-1598-6-2-1</Coordinate><ConfidenceRateList>-30</ConfidenceRateList></Entity></Line><Line nb="89" /></Page></CoordinateList>